growpy/__init__.py
growpy/models.py
growpy/objectives.py
growpy/selfstarts.py
growpy-0.0.12.dist-info/LICENSE
growpy-0.0.12.dist-info/METADATA
growpy-0.0.12.dist-info/WHEEL
growpy-0.0.12.dist-info/top_level.txt
growpy-0.0.12.dist-info/RECORD
